setup.py
PyVDF/__init__.py
PyVDF.egg-info/PKG-INFO
PyVDF.egg-info/SOURCES.txt
PyVDF.egg-info/dependency_links.txt
PyVDF.egg-info/top_level.txt