Metadata-Version: 1.1
Name: PyVDF
Version: 2.0.0
Summary: Python Library for reading VDFs and Valve KeyValue files
Home-page: https://github.com/amreuland/PyVDF
Author: Austin Reuland
Author-email: amreuland@gmail.com
License: MIT
Keywords: VDF KeyValues Valve
Platform: any
Classifier: Development Status :: 4 - Beta
Classifier: Environment :: Console
Classifier: Intended Audience :: Developers
Classifier: License :: OSI Approved :: MIT License
Classifier: Natural Language :: English
Classifier: Operating System :: OS Independent
Classifier: Programming Language :: Python :: 2.7
Classifier: Programming Language :: Python :: 3.2
Classifier: Programming Language :: Python :: 3.3
Classifier: Programming Language :: Python :: 3.4
Classifier: Topic :: Software Development :: Libraries :: Python Modules
Classifier: Topic :: Text Processing
Classifier: Topic :: Utilities
